README.md
setup.py
MineAPI.egg-info/PKG-INFO
MineAPI.egg-info/SOURCES.txt
MineAPI.egg-info/dependency_links.txt
MineAPI.egg-info/requires.txt
MineAPI.egg-info/top_level.txt
bedrock/__init__.py
bedrock/MCStatus/__init__.py
bedrock/MCStatus/main.py
bedrock/hive/__init__.py
bedrock/hive/main.py
java/__init__.py
java/MCStatus/__init__.py
java/MCStatus/main.py