Metadata-Version: 2.1
Name: MineAPI
Version: 0.0.1
Summary: A MCServer API Wrapper.
Home-page: https://github.com/sonyakun/MCAPI
Author: sonyakun
Author-email: sonyakun217@gmail.com
License: UNKNOWN
Platform: UNKNOWN
Classifier: Programming Language :: Python :: 3
Classifier: License :: OSI Approved :: MIT License
Classifier: Operating System :: OS Independent
Requires-Python: >=3.10
